rfc1751.py
rfc1751-1.0.0.dist-info/METADATA
rfc1751-1.0.0.dist-info/WHEEL
rfc1751-1.0.0.dist-info/RECORD
