Metadata-Version: 2.1
Name: rfc1751
Version: 1.0.0
Summary: Pure Python implementation of the binary-to-text encoding from RFC 1751, S/Key
Home-page: https://github.com/remram44/python-rfc1751
License: MIT
Keywords: binary,encoding,skey,s/key,rfc1751,1751
Author: Remi Rampin
Author-email: remi@rampin.org
Requires-Python: >=3.8,<4.0
Classifier: Development Status :: 4 - Beta
Classifier: License :: OSI Approved :: MIT License
Classifier: Natural Language :: English
Classifier: Programming Language :: Python :: 3
Classifier: Programming Language :: Python :: 3.8
Classifier: Programming Language :: Python :: 3.9
Classifier: Programming Language :: Python :: 3.10
Classifier: Programming Language :: Python :: 3.11
Classifier: Programming Language :: Python :: 3 :: Only
Classifier: Topic :: Text Processing
Project-URL: Bug Tracker, https://github.com/remram44/python-rfc1751/issues
Project-URL: Repository, https://github.com/remram44/python-rfc1751
